aioqueuerpc/__init__.py
aioqueuerpc/job_spec.py
aioqueuerpc/jsonrpc_schemas.py
aioqueuerpc/rpc.py
aioqueuerpc/worker.py
aioqueuerpc-0.2.0.dist-info/LICENSE
aioqueuerpc-0.2.0.dist-info/METADATA
aioqueuerpc-0.2.0.dist-info/WHEEL
aioqueuerpc-0.2.0.dist-info/top_level.txt
aioqueuerpc-0.2.0.dist-info/RECORD
